agent_spy/__init__.py
agent_spy/cost_calculator.py
agent_spy/logger.py
agent_spy/monitor.py
agent_spy/old_monitor.py
agent_spy/utils.py
agent_spy/visualizer.py
agent_spy_monitor-0.1.0.dist-info/licenses/LICENSE
agent_spy_monitor-0.1.0.dist-info/METADATA
agent_spy_monitor-0.1.0.dist-info/WHEEL
agent_spy_monitor-0.1.0.dist-info/top_level.txt
agent_spy_monitor-0.1.0.dist-info/RECORD
