Metadata-Version: 2.4
Name: agent-spy-monitor
Version: 0.1.0
Summary: An operational monitoring library for AI agent applications
Author-email: Nidhish Wakodikar <nidhishwakodikar@gmail.com>
License: MIT
Project-URL: Homepage, https://github.com/nidhishwakodikar/agent-spy-monitor
Project-URL: Repository, https://github.com/nidhishwakodikar/agent-spy-monitor
Project-URL: Issues, https://github.com/nidhishwakodikar/agent-spy-monitor/issues
Project-URL: Documentation, https://github.com/nidhishwakodikar/agent-spy-monitor#readme
Keywords: ai,agent,monitoring,tokens,cost,performance
Classifier: Development Status :: 3 - Alpha
Classifier: Intended Audience :: Developers
Classifier: License :: OSI Approved :: MIT License
Classifier: Operating System :: OS Independent
Classifier: Programming Language :: Python :: 3
Classifier: Programming Language :: Python :: 3.8
Classifier: Programming Language :: Python :: 3.9
Classifier: Programming Language :: Python :: 3.10
Classifier: Programming Language :: Python :: 3.11
Classifier: Programming Language :: Python :: 3.12
Classifier: Topic :: Software Development :: Libraries :: Python Modules
Classifier: Topic :: System :: Monitoring
Requires-Python: >=3.8
License-File: LICENSE
Requires-Dist: matplotlib>=3.5.0
Requires-Dist: psutil>=5.8.0
Requires-Dist: streamlit>=1.20.0
Requires-Dist: tiktoken>=0.4.0
Provides-Extra: test
Requires-Dist: pytest>=7.0.0; extra == "test"
Requires-Dist: pytest-cov>=4.0.0; extra == "test"
Provides-Extra: dev
Requires-Dist: black; extra == "dev"
Requires-Dist: flake8; extra == "dev"
Requires-Dist: mypy; extra == "dev"
Dynamic: license-file
